skim_unicode_table-0.1.21.dist-info/LICENSE
skim_unicode_table-0.1.21.dist-info/WHEEL
skim_unicode_table-0.1.21.dist-info/top_level.txt
skim_unicode_table-0.1.21.dist-info/RECORD
skim_unicode_table-0.1.21.dist-info/METADATA
skim_unicode_table/run.sh
skim_unicode_table/print-unicode-table
skim_unicode_table/run-xsel.sh
skim_unicode_table/render-glyph
skim_unicode_table/__init__.py
skim_unicode_table/sk
skim_unicode_table-0.1.21.data/scripts/skim-unicode-table
skim_unicode_table-0.1.21.data/scripts/skim-unicode-table-xsel
