Metadata-Version: 2.1
Name: skim-unicode-table
Version: 0.1.21
Summary: Interactive fuzzy-searchable unicode table using lotabout/skim
Home-page: https://github.com/smheidrich/skim-unicode-table
Author: Shahriar Heidrich
Author-email: smheidrich@weltenfunktion.de
Keywords: unicode,table,interactive,character,fuzzy
Classifier: Development Status :: 3 - Alpha
Classifier: Environment :: Console
Classifier: Operating System :: POSIX :: Linux
Classifier: Programming Language :: Python :: 3.9
Classifier: Programming Language :: Python :: 3.10
Classifier: Programming Language :: Python :: 3.11
License-File: LICENSE
Requires-Dist: cairocffi
Requires-Dist: pangocairocffi
